LICENSE
README.md
pyproject.toml
setup.py
src/aws_hashicorp_packer_reaper/__init__.py
src/aws_hashicorp_packer_reaper/__main__.py
src/aws_hashicorp_packer_reaper/aws.py
src/aws_hashicorp_packer_reaper/click_argument_types.py
src/aws_hashicorp_packer_reaper/logger.py
src/aws_hashicorp_packer_reaper/reaper.py
src/aws_hashicorp_packer_reaper/schema.py
src/aws_hashicorp_packer_reaper.egg-info/PKG-INFO
src/aws_hashicorp_packer_reaper.egg-info/SOURCES.txt
src/aws_hashicorp_packer_reaper.egg-info/dependency_links.txt
src/aws_hashicorp_packer_reaper.egg-info/entry_points.txt
src/aws_hashicorp_packer_reaper.egg-info/not-zip-safe
src/aws_hashicorp_packer_reaper.egg-info/requires.txt
src/aws_hashicorp_packer_reaper.egg-info/top_level.txt